noclouddotnet/__init__.py
noclouddotnet/app.py
noclouddotnet/app.wsgi
noclouddotnet/metaserver.db
noclouddotnet/models.py
noclouddotnet/nocloud.net.db
noclouddotnet/utils.py
noclouddotnet/instance/__init__.py
noclouddotnet/instance/instanceid.py
noclouddotnet/instance/routes.py
noclouddotnet-1.0.5.dist-info/LICENSE
noclouddotnet-1.0.5.dist-info/METADATA
noclouddotnet-1.0.5.dist-info/WHEEL
noclouddotnet-1.0.5.dist-info/entry_points.txt
noclouddotnet-1.0.5.dist-info/test_info.txt
noclouddotnet-1.0.5.dist-info/top_level.txt
noclouddotnet-1.0.5.dist-info/RECORD
