Metadata-Version: 2.1
Name: noclouddotnet
Version: 1.0.5
Summary: NoCloudNet Datasource/Metadata server for cloud-init
Home-page: http://linux.last-bastion.net
Author: Alan Milligan
Author-email: alan.milligan@last-bastion.net
License: GPL
Project-URL: Documentation, https://noclouddotnet.readthedocs.io/
Project-URL: Source, https://github.com/milligana/noclouddotnet/
Project-URL: Tracker, https://github.com/milligana/noclouddotnet/issues
Platform: UNKNOWN
Classifier: Framework :: Flask
Classifier: Programming Language :: Python :: 3
Classifier: Development Status :: 5 - Production/Stable
Classifier: License :: OSI Approved :: GNU General Public License v3 (GPLv3)
Classifier: Topic :: Internet :: WWW/HTTP :: WSGI :: Server
Classifier: Topic :: System :: Boot :: Init
Classifier: Topic :: System :: Operating System Kernels :: Linux
Requires-Dist: Flask (>=2.0)
Requires-Dist: PyYAML
Requires-Dist: Flask-Migrate
Requires-Dist: dynaconf
Requires-Dist: dnspython
Requires-Dist: prometheus-flask-exporter
Requires-Dist: stevedore
Provides-Extra: jaeger
Requires-Dist: Flask-OpenTracing ; extra == 'jaeger'
Requires-Dist: jaeger-client ; extra == 'jaeger'
Provides-Extra: prospector
Requires-Dist: prospector[with_everything] ; extra == 'prospector'
Provides-Extra: test
Requires-Dist: tox ; extra == 'test'
Requires-Dist: pytest-cov ; extra == 'test'
Requires-Dist: pytest-flask ; extra == 'test'
